itex/__init__.py
itex-0.0.0.dist-info/LICENSE.txt
itex-0.0.0.dist-info/WHEEL
itex-0.0.0.dist-info/METADATA
itex-0.0.0.dist-info/RECORD
