Metadata-Version: 2.1
Name: itex
Version: 0.0.0
Summary: iTeX
License: GPL-3.0-only
Author: iydon
Author-email: liangiydon@gmail.com
Requires-Python: >=3.8,<4.0
Classifier: License :: OSI Approved :: GNU General Public License v3 (GPLv3)
Classifier: Programming Language :: Python :: 3
Classifier: Programming Language :: Python :: 3.10
Classifier: Programming Language :: Python :: 3.8
Classifier: Programming Language :: Python :: 3.9
